graphcap/__init__.py
graphcap/job_manager.py
graphcap/main.py
graphcap/caption/__init__.py
graphcap/caption/base_caption.py
graphcap/caption/batch_config.py
graphcap/caption/nodes/__init__.py
graphcap/caption/nodes/output.py
graphcap/caption/nodes/perspective.py
graphcap/caption/perspectives/__init__.py
graphcap/caption/perspectives/base.py
graphcap/caption/perspectives/art_critic/__init__.py
graphcap/caption/perspectives/art_critic/processor.py
graphcap/caption/perspectives/art_critic/report.py
graphcap/caption/perspectives/art_critic/types.py
graphcap/caption/perspectives/art_critic/templates/art_report.html
graphcap/caption/perspectives/graph/__init__.py
graphcap/caption/perspectives/graph/network.py
graphcap/caption/perspectives/graph/processor.py
graphcap/caption/perspectives/graph/report.py
graphcap/caption/perspectives/graph/types.py
graphcap/caption/perspectives/graph/templates/graph_report.html
graphcap/caption/templates/graph_report.html
graphcap/dag/README.md
graphcap/dag/__init__.py
graphcap/dag/dag.py
graphcap/dag/node.py
graphcap/dag/nodes/__init__.py
graphcap/dag/nodes/meta.py
graphcap/dag/nodes/visualizer.py
graphcap/dataset/__init__.py
graphcap/dataset/dataset_manager.py
graphcap/dataset/file_handler.py
graphcap/dataset/hf_client.py
graphcap/dataset/metadata.py
graphcap/dataset/nodes/__init__.py
graphcap/dataset/nodes/export.py
graphcap/io/__init__.py
graphcap/io/nodes/__init__.py
graphcap/io/nodes/image_sampling.py
graphcap/providers/README.md
graphcap/providers/__init__.py
graphcap/providers/provider_config.py
graphcap/providers/provider_manager.py
graphcap/providers/clients/__init__.py
graphcap/providers/clients/base_client.py
graphcap/providers/clients/gemini_client.py
graphcap/providers/clients/ollama_client.py
graphcap/providers/clients/openai_client.py
graphcap/providers/clients/openrouter_client.py
graphcap/providers/clients/vllm_client.py
graphcap/schemas/__init__.py
graphcap/schemas/caption.py
graphcap/schemas/structured_vision.py
graphcap-0.0.2.dist-info/METADATA
graphcap-0.0.2.dist-info/WHEEL
graphcap-0.0.2.dist-info/entry_points.txt
graphcap-0.0.2.dist-info/RECORD
