Metadata-Version: 2.4
Name: graphcap
Version: 0.0.2
Summary: graphcap
Requires-Python: >=3.11
Requires-Dist: alembic>=1.14.1
Requires-Dist: click>=8.1.8
Requires-Dist: datasets>=3.2.0
Requires-Dist: fastapi>=0.115.6
Requires-Dist: httpx>=0.28.1
Requires-Dist: huggingface-hub>=0.27.1
Requires-Dist: jinja2>=3.1.5
Requires-Dist: loguru>=0.7.3
Requires-Dist: matplotlib>=3.10.0
Requires-Dist: networkx>=3.4.2
Requires-Dist: openai>=1.59.9
Requires-Dist: pydantic>=2.10.5
Requires-Dist: python-dotenv>=1.0.1
Requires-Dist: python-multipart>=0.0.20
Requires-Dist: pyvis>=0.3.2
Requires-Dist: rich>=13.9.4
Requires-Dist: scipy>=1.15.1
Requires-Dist: tenacity>=9.0.0
Requires-Dist: termcolor>=2.5.0
Requires-Dist: uvicorn>=0.34.0
Provides-Extra: test
Requires-Dist: basedpyright>=1.26.0; extra == 'test'
Requires-Dist: pytest-asyncio>=0.21.0; extra == 'test'
Requires-Dist: pytest-cov>=4.1.0; extra == 'test'
Requires-Dist: pytest-watcher>=0.4.3; extra == 'test'
Requires-Dist: pytest>=7.0.0; extra == 'test'
